extremal_python_dependencies/__init__.py
extremal_python_dependencies/main.py
extremal_python_dependencies-0.1.0.dist-info/METADATA
extremal_python_dependencies-0.1.0.dist-info/WHEEL
extremal_python_dependencies-0.1.0.dist-info/entry_points.txt
extremal_python_dependencies-0.1.0.dist-info/licenses/LICENSE.txt
extremal_python_dependencies-0.1.0.dist-info/RECORD
