Metadata-Version: 2.4
Name: extremal-python-dependencies
Version: 0.1.0
Summary: A utility for installing extremal versions of dependencies for more robust testing
License:                                  Apache License
License-File: LICENSE.txt
Classifier: Development Status :: 3 - Alpha
Classifier: Intended Audience :: Developers
Classifier: License :: OSI Approved :: Apache Software License
Classifier: Natural Language :: English
Classifier: Operating System :: MacOS
Classifier: Operating System :: Microsoft :: Windows
Classifier: Operating System :: POSIX :: Linux
Classifier: Programming Language :: Python :: 3.10
Classifier: Programming Language :: Python :: 3.11
Classifier: Programming Language :: Python :: 3.12
Classifier: Programming Language :: Python :: 3.13
Requires-Python: >=3.10
Requires-Dist: click==8.3.0
Requires-Dist: toml==0.10.2
Requires-Dist: typer==0.19.1
Provides-Extra: dev
Requires-Dist: mypy==1.15.0; extra == 'dev'
Requires-Dist: pydocstyle==6.3.0; extra == 'dev'
Requires-Dist: pylint==3.3.8; extra == 'dev'
Requires-Dist: pytest>=7.4.4; extra == 'dev'
Requires-Dist: reno>=4.1; extra == 'dev'
Requires-Dist: ruff==0.12.11; extra == 'dev'
Requires-Dist: types-toml~=0.10.8.20240310; extra == 'dev'
Requires-Dist: typos>=1.20.0; extra == 'dev'
Provides-Extra: lint
Requires-Dist: mypy==1.15.0; extra == 'lint'
Requires-Dist: pydocstyle==6.3.0; extra == 'lint'
Requires-Dist: pylint==3.3.8; extra == 'lint'
Requires-Dist: reno>=4.1; extra == 'lint'
Requires-Dist: ruff==0.12.11; extra == 'lint'
Requires-Dist: types-toml~=0.10.8.20240310; extra == 'lint'
Requires-Dist: typos>=1.20.0; extra == 'lint'
Provides-Extra: style
Requires-Dist: ruff==0.12.11; extra == 'style'
Requires-Dist: typos>=1.20.0; extra == 'style'
Provides-Extra: test
Requires-Dist: pytest>=7.4.4; extra == 'test'
